pandasai_snowflake/__init__.py
pandasai_snowflake-0.1.5.dist-info/LICENSE
pandasai_snowflake-0.1.5.dist-info/METADATA
pandasai_snowflake-0.1.5.dist-info/WHEEL
pandasai_snowflake-0.1.5.dist-info/RECORD
